JsonValidator.py
robotframework_jsonvalidator-2.0.0.dist-info/LICENSE
robotframework_jsonvalidator-2.0.0.dist-info/METADATA
robotframework_jsonvalidator-2.0.0.dist-info/WHEEL
robotframework_jsonvalidator-2.0.0.dist-info/top_level.txt
robotframework_jsonvalidator-2.0.0.dist-info/RECORD
