Metadata-Version: 1.1
Name: robotframework-jsonvalidator
Version: 2.0.0
Summary: A Robot Framework JSON Validator Library
Home-page: https://github.com/peterservice-rnd/robotframework-jsonvalidator
Author: JSC PETER-SERVICE
Author-email: drse_aist_all@billing.ru
License: Apache License, Version 2.0
Keywords: testing robotframework json jsonschema jsonpath jsonselect
Platform: UNKNOWN
Classifier: Development Status :: 5 - Production/Stable
Classifier: Intended Audience :: Developers
Classifier: Topic :: Software Development :: Testing
Classifier: License :: OSI Approved :: Apache Software License
Classifier: Programming Language :: Python :: 3.5
Classifier: Programming Language :: Python :: 3.6
Classifier: Framework :: Robot Framework :: Library
